__init__.py
__main__.py
drmp-0.0.0.dist-info/METADATA
drmp-0.0.0.dist-info/WHEEL
drmp-0.0.0.dist-info/RECORD
