Metadata-Version: 2.1
Name: drmp
Version: 0.0.0
Summary: Debian Repository Mirror Profile
Author-email: Marc Beninca <git@marc.beninca.link>
Maintainer-email: Marc Beninca <git@marc.beninca.link>
Classifier: License :: OSI Approved :: GNU Affero General Public License v3
Classifier: Operating System :: OS Independent
Classifier: Programming Language :: Python :: 3
Requires-Python: >=3.6
